json2sql/__init__.py
json2sql/errors.py
json2sql/json2sql.py
json2sql/select.py
json2sql/utils.py
json2sql-1.0.0rc1.dist-info/DESCRIPTION.rst
json2sql-1.0.0rc1.dist-info/METADATA
json2sql-1.0.0rc1.dist-info/RECORD
json2sql-1.0.0rc1.dist-info/WHEEL
json2sql-1.0.0rc1.dist-info/metadata.json
json2sql-1.0.0rc1.dist-info/top_level.txt
